[
    {
        "sector": "corrales",
        "numeroDeGrifo": "1",
        "ubicacionDelGrifo": "lavamanos bajada animales",
        "estado": "3/5/2024",
        "frecuenciaDeMuestreo": "anual"
    },
    {
        "sector": "corrales",
        "numeroDeGrifo": "2",
        "ubicacionDelGrifo": "lavamanos cepo",
        "estado": "10/5/2024",
        "frecuenciaDeMuestreo": "anual"
    },
    {
        "sector": "corrales",
        "numeroDeGrifo": "3",
        "ubicacionDelGrifo": "lavamanos cepo ue",
        "estado": "10/5/2024",
        "frecuenciaDeMuestreo": "anual"
    },
    {
        "sector": "corrales",
        "numeroDeGrifo": "4",
        "ubicacionDelGrifo": "lavamanos vestuario",
        "estado": "10/5/2024",
        "frecuenciaDeMuestreo": "anual"
    },
    {
        "sector": "corrales",
        "numeroDeGrifo": "5",
        "ubicacionDelGrifo": "lavamanos digestor",
        "estado": "10/5/24 rodillera de grifo rota",
        "frecuenciaDeMuestreo": "anual"
    },
    {
        "sector": "corrales",
        "numeroDeGrifo": "6",
        "ubicacionDelGrifo": "lavamanos necropsia",
        "estado": "3/5/2024 jabonera rota/ lava botas no funciona",
        "frecuenciaDeMuestreo": "anual"
    },
    {
        "sector": "corrales",
        "numeroDeGrifo": "10",
        "ubicacionDelGrifo": "lavamanos playa de emergencia/esterilizador",
        "estado": "3/5/2024 funciona continuo(no corta)",
        "frecuenciaDeMuestreo": "anual"
    },
    {
        "sector": "corrales",
        "numeroDeGrifo": "11",
        "ubicacionDelGrifo": "lavamanos playa de emergencia/esterilizador",
        "estado": "3/5/2024 desague tapado",
        "frecuenciaDeMuestreo": "anual"
    },
    {
        "sector": "corrales",
        "numeroDeGrifo": "12",
        "ubicacionDelGrifo": "pico - playa de emergencia",
        "estado": "3/1/24 alambres con oxido 9/2/2024 28/3/2024- 12/04/24//3/5/24",
        "frecuenciaDeMuestreo": "anual"
    },
    {
        "sector": "corrales",
        "numeroDeGrifo": "13",
        "ubicacionDelGrifo": "pico - playa de emergencia",
        "estado": "3/5/2024 presencia de oxido",
        "frecuenciaDeMuestreo": "anual"
    },
    {
        "sector": "corrales",
        "numeroDeGrifo": "14",
        "ubicacionDelGrifo": "lavamanos playa de emergencia/ esterilizador",
        "estado": "3/5/2024 perida de agua, no funciona rodillera",
        "frecuenciaDeMuestreo": "anual"
    },
    {
        "sector": "mondongueria",
        "numeroDeGrifo": "34",
        "ubicacionDelGrifo": "lavamanos-filtro sanitario",
        "estado": "3/5/2024 falta cepillo y cadena",
        "frecuenciaDeMuestreo": "anual"
    },
    {
        "sector": "despacho menudencias",
        "numeroDeGrifo": "35",
        "ubicacionDelGrifo": "pico - sala/alimentación de bateas y duchas",
        "estado": "3/5/2024 presencia de oxido",
        "frecuenciaDeMuestreo": "trimestral"
    },
    {
        "sector": "despacho menudencias",
        "numeroDeGrifo": "36",
        "ubicacionDelGrifo": "lavamanos /esterilizador",
        "estado": "12/4/2024 jabonera rota",
        "frecuenciaDeMuestreo": "anual"
    },
    {
        "sector": "despacho menudencias",
        "numeroDeGrifo": "37",
        "ubicacionDelGrifo": "pico - sala",
        "estado": "3/5/2024",
        "frecuenciaDeMuestreo": "anual"
    },
    {
        "sector": "mondongueria",
        "numeroDeGrifo": "38",
        "ubicacionDelGrifo": "pico - sala",
        "estado": "3/5/2024",
        "frecuenciaDeMuestreo": "semestral"
    },
    {
        "sector": "mondongueria",
        "numeroDeGrifo": "39",
        "ubicacionDelGrifo": "pico - sala",
        "estado": "3/5/2024",
        "frecuenciaDeMuestreo": "semestral"
    },
    {
        "sector": "mondongueria",
        "numeroDeGrifo": "40",
        "ubicacionDelGrifo": "pico - sala/ alimentación de cocinas",
        "estado": "3/5/2024",
        "frecuenciaDeMuestreo": "trimestral"
    },
    {
        "sector": "despacho menudencias",
        "numeroDeGrifo": "41",
        "ubicacionDelGrifo": "pico-dock carga",
        "estado": "3/5/2024",
        "frecuenciaDeMuestreo": "semestral"
    },
    {
        "sector": "triperia",
        "numeroDeGrifo": "42",
        "ubicacionDelGrifo": "lavamanos -filtro sanitario",
        "estado": "3/5/2024",
        "frecuenciaDeMuestreo": "anual"
    },
    {
        "sector": "triperia",
        "numeroDeGrifo": "43",
        "ubicacionDelGrifo": "lavamanos-filtro sanitario",
        "estado": "3/5/2024",
        "frecuenciaDeMuestreo": "anual"
    },
    {
        "sector": "triperia",
        "numeroDeGrifo": "44",
        "ubicacionDelGrifo": "lavamanos-sector",
        "estado": "3/5/2024",
        "frecuenciaDeMuestreo": "semestral"
    },
    {
        "sector": "triperia",
        "numeroDeGrifo": "45",
        "ubicacionDelGrifo": "lavamanos -sector/ alimentación de duchas de toda la línea",
        "estado": "3/5/2024",
        "frecuenciaDeMuestreo": "trimestral"
    },
    {
        "sector": "triperia",
        "numeroDeGrifo": "46",
        "ubicacionDelGrifo": "lavamanos-sector",
        "estado": "3/5/2024",
        "frecuenciaDeMuestreo": "semestral"
    },
    {
        "sector": "vestuario senasa",
        "numeroDeGrifo": "47",
        "ubicacionDelGrifo": "lavamanos-baño",
        "estado": "3/5/2024",
        "frecuenciaDeMuestreo": "anual"
    },
    {
        "sector": "faena vestuario",
        "numeroDeGrifo": "48",
        "ubicacionDelGrifo": "lavamanos -filtro sanitario baño",
        "estado": "3/5/2024",
        "frecuenciaDeMuestreo": "anual"
    },
    {
        "sector": "faena vestuario",
        "numeroDeGrifo": "50",
        "ubicacionDelGrifo": "lavamanos-baño zona intermedia",
        "estado": "10/5/2024",
        "frecuenciaDeMuestreo": "anual"
    },
    {
        "sector": "comedor",
        "numeroDeGrifo": "51",
        "ubicacionDelGrifo": "lavadero-cocina",
        "estado": "10/5/2024",
        "frecuenciaDeMuestreo": "anual"
    },
    {
        "sector": "comedor",
        "numeroDeGrifo": "52",
        "ubicacionDelGrifo": "lavadero-cocina",
        "estado": "10/5/2024",
        "frecuenciaDeMuestreo": "anual"
    },
    {
        "sector": "comedor",
        "numeroDeGrifo": "53",
        "ubicacionDelGrifo": "lavamanos-baño privado",
        "estado": "10/5/2024",
        "frecuenciaDeMuestreo": "anual"
    },
    {
        "sector": "lavadero",
        "numeroDeGrifo": "54",
        "ubicacionDelGrifo": "lavamanos",
        "estado": "10/5/2024",
        "frecuenciaDeMuestreo": "semestral"
    },
    {
        "sector": "faena zona sucia",
        "numeroDeGrifo": "56",
        "ubicacionDelGrifo": "lavamanos filtro noqueo kosher",
        "estado": "10/5/2024",
        "frecuenciaDeMuestreo": "semestral"
    },
    {
        "sector": "faena zona sucia",
        "numeroDeGrifo": "57",
        "ubicacionDelGrifo": "pico - noqueo kosher",
        "estado": "10/5/2024",
        "frecuenciaDeMuestreo": "semestral"
    },
    {
        "sector": "vestuario kosher",
        "numeroDeGrifo": "58",
        "ubicacionDelGrifo": "lavamanos baño vestuario kosher",
        "estado": "10/5/2024",
        "frecuenciaDeMuestreo": "anual"
    },
    {
        "sector": "vestuario kosher",
        "numeroDeGrifo": "59",
        "ubicacionDelGrifo": "lavamanos",
        "estado": "10/5/2024",
        "frecuenciaDeMuestreo": "anual"
    },
    {
        "sector": "depósito de sal",
        "numeroDeGrifo": "60",
        "ubicacionDelGrifo": "lavamanos",
        "estado": "10/5/2024",
        "frecuenciaDeMuestreo": "anual"
    },
    {
        "sector": "faena zona sucia",
        "numeroDeGrifo": "61",
        "ubicacionDelGrifo": "lavamanos palco noqueo kosher/ esterilizador",
        "estado": "10/5/2024",
        "frecuenciaDeMuestreo": "semestral"
    },
    {
        "sector": "faena zona sucia",
        "numeroDeGrifo": "62",
        "ubicacionDelGrifo": "lavamanos maneador",
        "estado": "10/5/2024",
        "frecuenciaDeMuestreo": "semestral"
    },
    {
        "sector": "corrales",
        "numeroDeGrifo": "63",
        "ubicacionDelGrifo": "piletas bebederos 1-17-18",
        "estado": "3/1/24 presencia de oxido 9/2/2024 28/3/2024-11/4/2024-3/5/24",
        "frecuenciaDeMuestreo": "trimestral"
    },
    {
        "sector": "corrales",
        "numeroDeGrifo": "65",
        "ubicacionDelGrifo": "picos-corrales",
        "estado": "3/5/24 presencia de oxido",
        "frecuenciaDeMuestreo": "anual"
    },
    {
        "sector": "roldanas",
        "numeroDeGrifo": "67",
        "ubicacionDelGrifo": "pico roldanas",
        "estado": "3/1/2024 presencia de oxido 9/2/2024 28/3/2024-11/4/2024/3/5/24",
        "frecuenciaDeMuestreo": "anual"
    },
    {
        "sector": "corrales",
        "numeroDeGrifo": "78",
        "ubicacionDelGrifo": "pico lavado",
        "estado": "3/1/24 presencia de oxido 9/2/2024 28/3/2024-11/4/2024..3/5/24",
        "frecuenciaDeMuestreo": null
    },
    {
        "sector": "faena",
        "numeroDeGrifo": "100",
        "ubicacionDelGrifo": "corta pata / manos lavamanos/esterilizador",
        "estado": null,
        "frecuenciaDeMuestreo": null
    },
    {
        "sector": "faena",
        "numeroDeGrifo": "101",
        "ubicacionDelGrifo": "lavamanos inspección veterinaria (tendones)/esterilizador",
        "estado": null,
        "frecuenciaDeMuestreo": "semestral"
    },
    {
        "sector": "faena",
        "numeroDeGrifo": "102",
        "ubicacionDelGrifo": "lavamanos garreo manos/esterilizador",
        "estado": null,
        "frecuenciaDeMuestreo": "semestral"
    },
    {
        "sector": "faena",
        "numeroDeGrifo": "103",
        "ubicacionDelGrifo": "lavamanos palco garreo patas/esterilizador",
        "estado": null,
        "frecuenciaDeMuestreo": "semestral"
    },
    {
        "sector": "faena",
        "numeroDeGrifo": "104",
        "ubicacionDelGrifo": "lavamanos palco garreo patas/esterilizador",
        "estado": null,
        "frecuenciaDeMuestreo": "semestral"
    },
    {
        "sector": "faena",
        "numeroDeGrifo": "105",
        "ubicacionDelGrifo": "lavamanos palco berija/esterilizador",
        "estado": null,
        "frecuenciaDeMuestreo": "semestral"
    },
    {
        "sector": "faena",
        "numeroDeGrifo": "106",
        "ubicacionDelGrifo": "lavamanos palco berija/esterilizador",
        "estado": null,
        "frecuenciaDeMuestreo": "semestral"
    },
    {
        "sector": "faena",
        "numeroDeGrifo": "107",
        "ubicacionDelGrifo": "lavamanos palco corta patas/esterilizador",
        "estado": null,
        "frecuenciaDeMuestreo": "semestral"
    },
    {
        "sector": "faena",
        "numeroDeGrifo": "108",
        "ubicacionDelGrifo": "pico zona garreo (limpieza)",
        "estado": null,
        "frecuenciaDeMuestreo": "anual"
    },
    {
        "sector": "faena",
        "numeroDeGrifo": "109",
        "ubicacionDelGrifo": "lavamanos matambrero/esterilizador",
        "estado": null,
        "frecuenciaDeMuestreo": "semestral"
    },
    {
        "sector": "faena",
        "numeroDeGrifo": "110",
        "ubicacionDelGrifo": "lavamanos matambrero/esterilizador",
        "estado": null,
        "frecuenciaDeMuestreo": "semestral"
    },
    {
        "sector": "faena",
        "numeroDeGrifo": "111",
        "ubicacionDelGrifo": "lavamanos desollador/esterilizador",
        "estado": null,
        "frecuenciaDeMuestreo": "semestral"
    },
    {
        "sector": "faena",
        "numeroDeGrifo": "112",
        "ubicacionDelGrifo": "lavamanos atado de culata/esterilizador",
        "estado": null,
        "frecuenciaDeMuestreo": "semestral"
    },
    {
        "sector": "faena",
        "numeroDeGrifo": "113",
        "ubicacionDelGrifo": "lavamanos gancho de culata/esterilizador",
        "estado": null,
        "frecuenciaDeMuestreo": "semestral"
    },
    {
        "sector": "faena",
        "numeroDeGrifo": "114",
        "ubicacionDelGrifo": "lavamanos cuereado de cabeza/esterilizador",
        "estado": null,
        "frecuenciaDeMuestreo": "semestral"
    },
    {
        "sector": "faena",
        "numeroDeGrifo": "115",
        "ubicacionDelGrifo": "registro\npico zona cuereado (limpieza)",
        "estado": null,
        "frecuenciaDeMuestreo": "anual"
    },
    {
        "sector": "faena",
        "numeroDeGrifo": "116",
        "ubicacionDelGrifo": "lavamanos brazuelo/esterilizador",
        "estado": null,
        "frecuenciaDeMuestreo": "semestral               2"
    },
    {
        "sector": "faena",
        "numeroDeGrifo": "117",
        "ubicacionDelGrifo": "lavamanos zona de cogotes (alternativo)/esterilizador",
        "estado": null,
        "frecuenciaDeMuestreo": "semestral"
    },
    {
        "sector": "faena",
        "numeroDeGrifo": "118",
        "ubicacionDelGrifo": "lavamanos cogotero/esterilizador",
        "estado": null,
        "frecuenciaDeMuestreo": "semestral"
    },
    {
        "sector": "faena",
        "numeroDeGrifo": "119",
        "ubicacionDelGrifo": "lavamanos dentición",
        "estado": null,
        "frecuenciaDeMuestreo": "semestral"
    },
    {
        "sector": "faena",
        "numeroDeGrifo": "120",
        "ubicacionDelGrifo": "lavamanos bajada cuero/esterilizador",
        "estado": null,
        "frecuenciaDeMuestreo": "semestral"
    },
    {
        "sector": "faena",
        "numeroDeGrifo": "121",
        "ubicacionDelGrifo": "lavamanos desnucado/esterilizador",
        "estado": null,
        "frecuenciaDeMuestreo": "semestral"
    },
    {
        "sector": "faena",
        "numeroDeGrifo": "121 a",
        "ubicacionDelGrifo": "esterilizador desnucado",
        "estado": null,
        "frecuenciaDeMuestreo": "semestral"
    },
    {
        "sector": "faena",
        "numeroDeGrifo": "122",
        "ubicacionDelGrifo": "lavamanos tirabuzón/esterilizador",
        "estado": null,
        "frecuenciaDeMuestreo": "semestral"
    },
    {
        "sector": "faena",
        "numeroDeGrifo": "123",
        "ubicacionDelGrifo": "lavamanos sierra de pecho/esterilizador",
        "estado": null,
        "frecuenciaDeMuestreo": "semestral"
    },
    {
        "sector": "faena",
        "numeroDeGrifo": "124",
        "ubicacionDelGrifo": "lavamanos colgado de cabeza/esterilizador",
        "estado": null,
        "frecuenciaDeMuestreo": "semestral"
    },
    {
        "sector": "faena",
        "numeroDeGrifo": "125",
        "ubicacionDelGrifo": "pico ducha lavado ganchos",
        "estado": null,
        "frecuenciaDeMuestreo": "semestral"
    },
    {
        "sector": "faena",
        "numeroDeGrifo": "126",
        "ubicacionDelGrifo": "pico lavado cabeza+lengua/ esterilizador",
        "estado": null,
        "frecuenciaDeMuestreo": "trimestral"
    },
    {
        "sector": "faena",
        "numeroDeGrifo": "127",
        "ubicacionDelGrifo": "lavamanos lengua/esterilizador",
        "estado": null,
        "frecuenciaDeMuestreo": "semestral"
    },
    {
        "sector": "faena",
        "numeroDeGrifo": "128",
        "ubicacionDelGrifo": "lavamanos inspeccion hígado/esterilizador",
        "estado": null,
        "frecuenciaDeMuestreo": "semestral"
    },
    {
        "sector": "faena",
        "numeroDeGrifo": "129",
        "ubicacionDelGrifo": "lavamanos revisión de galglios/esterilizador",
        "estado": null,
        "frecuenciaDeMuestreo": "semestral"
    },
    {
        "sector": "faena",
        "numeroDeGrifo": "130",
        "ubicacionDelGrifo": "lavamanos insp.veterinaria-bandeja de vísceras/esterilizador",
        "estado": null,
        "frecuenciaDeMuestreo": "semestral"
    },
    {
        "sector": "faena",
        "numeroDeGrifo": "131",
        "ubicacionDelGrifo": "lavamanos insp.veterinaria-bandeja de vísceras/esterilizador",
        "estado": null,
        "frecuenciaDeMuestreo": "semestral"
    },
    {
        "sector": "faena",
        "numeroDeGrifo": "132",
        "ubicacionDelGrifo": "lavamanos insp.veterinaria-bandeja de vísceras/esterilizador",
        "estado": null,
        "frecuenciaDeMuestreo": "semestral"
    },
    {
        "sector": "faena",
        "numeroDeGrifo": "133",
        "ubicacionDelGrifo": "lavamanos despanzado/esterilizador",
        "estado": null,
        "frecuenciaDeMuestreo": "semestral"
    },
    {
        "sector": "faena",
        "numeroDeGrifo": "134",
        "ubicacionDelGrifo": "lavamanos despanzado/esterilizador",
        "estado": null,
        "frecuenciaDeMuestreo": "semestral"
    },
    {
        "sector": "faena",
        "numeroDeGrifo": "135",
        "ubicacionDelGrifo": "pico zona intermedia (limpieza)",
        "estado": null,
        "frecuenciaDeMuestreo": "anual"
    },
    {
        "sector": "faena",
        "numeroDeGrifo": "136",
        "ubicacionDelGrifo": "lavamanos zona intermedia (alternativo)",
        "estado": null,
        "frecuenciaDeMuestreo": "anual"
    },
    {
        "sector": "faena",
        "numeroDeGrifo": "137",
        "ubicacionDelGrifo": "lavamanos palco sierra medias",
        "estado": null,
        "frecuenciaDeMuestreo": "trimestral"
    },
    {
        "sector": "faena",
        "numeroDeGrifo": "138",
        "ubicacionDelGrifo": "ducha lavado sierra medias/esterilizador",
        "estado": null,
        "frecuenciaDeMuestreo": "semestral"
    },
    {
        "sector": "faena",
        "numeroDeGrifo": "139",
        "ubicacionDelGrifo": "lavamanos pelado de entraña/ esterilizador",
        "estado": null,
        "frecuenciaDeMuestreo": "semestral"
    },
    {
        "sector": "faena",
        "numeroDeGrifo": "140",
        "ubicacionDelGrifo": "lavamanos vacuna y ganglios/esterilizador",
        "estado": null,
        "frecuenciaDeMuestreo": "semestral"
    },
    {
        "sector": "faena",
        "numeroDeGrifo": "141",
        "ubicacionDelGrifo": "lavamanos ganglio,matambre y cadera/esterilizador",
        "estado": null,
        "frecuenciaDeMuestreo": "semestral"
    },
    {
        "sector": "faena",
        "numeroDeGrifo": "142",
        "ubicacionDelGrifo": "lavamanos extracción de rabo y riñon/esterilizador",
        "estado": null,
        "frecuenciaDeMuestreo": "semestral"
    },
    {
        "sector": "faena",
        "numeroDeGrifo": "143",
        "ubicacionDelGrifo": "lavamanos remoción de sebos/esterilizador",
        "estado": null,
        "frecuenciaDeMuestreo": "semestral"
    },
    {
        "sector": "faena",
        "numeroDeGrifo": "144",
        "ubicacionDelGrifo": "pico (limpieza)",
        "estado": null,
        "frecuenciaDeMuestreo": "anual"
    },
    {
        "sector": "faena",
        "numeroDeGrifo": "145",
        "ubicacionDelGrifo": "lavamanos palco de médula/esterilizador",
        "estado": null,
        "frecuenciaDeMuestreo": "semestral"
    },
    {
        "sector": "faena",
        "numeroDeGrifo": "146",
        "ubicacionDelGrifo": "lavamanos pcc (opcional)/esterilizador",
        "estado": null,
        "frecuenciaDeMuestreo": "semestral"
    },
    {
        "sector": "faena",
        "numeroDeGrifo": "147",
        "ubicacionDelGrifo": "lavamanos pcc 1 alto/esterilizador",
        "estado": null,
        "frecuenciaDeMuestreo": "semestral"
    },
    {
        "sector": "faena",
        "numeroDeGrifo": "148",
        "ubicacionDelGrifo": "lavamanos pcc 1 bajo/esterilizador",
        "estado": null,
        "frecuenciaDeMuestreo": "semestral"
    },
    {
        "sector": "faena",
        "numeroDeGrifo": "149",
        "ubicacionDelGrifo": "pico lavado medias",
        "estado": null,
        "frecuenciaDeMuestreo": "trimestral"
    },
    {
        "sector": "faena",
        "numeroDeGrifo": "150",
        "ubicacionDelGrifo": "pico lavado medias",
        "estado": null,
        "frecuenciaDeMuestreo": "trimestral"
    },
    {
        "sector": "faena",
        "numeroDeGrifo": "151",
        "ubicacionDelGrifo": "lavamanos reinspeccion/esterilizador",
        "estado": null,
        "frecuenciaDeMuestreo": "semestral"
    },
    {
        "sector": "faena",
        "numeroDeGrifo": "152",
        "ubicacionDelGrifo": "lavamanos reinspeccion/esterilizador",
        "estado": null,
        "frecuenciaDeMuestreo": "anual"
    },
    {
        "sector": "faena",
        "numeroDeGrifo": "153",
        "ubicacionDelGrifo": "lavamanos reinspeccion/esterilizador",
        "estado": null,
        "frecuenciaDeMuestreo": "anual"
    },
    {
        "sector": "faena",
        "numeroDeGrifo": "154",
        "ubicacionDelGrifo": "esterilizador/cabina de acido lactico",
        "estado": null,
        "frecuenciaDeMuestreo": null
    },
    {
        "sector": "faena",
        "numeroDeGrifo": "155",
        "ubicacionDelGrifo": "esterilizador/pico lavado carros",
        "estado": "18/4/2024 presencia de oxido",
        "frecuenciaDeMuestreo": "anual"
    },
    {
        "sector": "faena",
        "numeroDeGrifo": "156",
        "ubicacionDelGrifo": "lavamanos filtro digestores",
        "estado": null,
        "frecuenciaDeMuestreo": "anual"
    },
    {
        "sector": "faena",
        "numeroDeGrifo": "157",
        "ubicacionDelGrifo": "esterilizador/ zona de reinspección (limpieza)",
        "estado": null,
        "frecuenciaDeMuestreo": "anual"
    },
    {
        "sector": "faena",
        "numeroDeGrifo": "158",
        "ubicacionDelGrifo": "pico digestor faena",
        "estado": null,
        "frecuenciaDeMuestreo": "anual"
    },
    {
        "sector": "faena",
        "numeroDeGrifo": "159",
        "ubicacionDelGrifo": "lavamanos digestor faena",
        "estado": null,
        "frecuenciaDeMuestreo": "anual"
    },
    {
        "sector": "faena",
        "numeroDeGrifo": "160",
        "ubicacionDelGrifo": "lavamanos palco tipificacion",
        "estado": null,
        "frecuenciaDeMuestreo": "semestral"
    },
    {
        "sector": "faena",
        "numeroDeGrifo": "161",
        "ubicacionDelGrifo": "lavamanos balanza-etiquetado/esterilizador",
        "estado": null,
        "frecuenciaDeMuestreo": "semestral"
    },
    {
        "sector": "faena",
        "numeroDeGrifo": "162",
        "ubicacionDelGrifo": "lavamanos y esterilizador cabina de acido lactico",
        "estado": null,
        "frecuenciaDeMuestreo": null
    },
    {
        "sector": "cámaras",
        "numeroDeGrifo": "163",
        "ubicacionDelGrifo": "lavamanos filtro sanitario camaras/esterilizador",
        "estado": "18/4/24 sin funcionar en general",
        "frecuenciaDeMuestreo": "anual"
    },
    {
        "sector": "cámaras",
        "numeroDeGrifo": "164",
        "ubicacionDelGrifo": "pico camaras",
        "estado": null,
        "frecuenciaDeMuestreo": "anual"
    },
    {
        "sector": "cámaras",
        "numeroDeGrifo": "165",
        "ubicacionDelGrifo": "pico camaras",
        "estado": null,
        "frecuenciaDeMuestreo": "anual"
    },
    {
        "sector": "faena",
        "numeroDeGrifo": "166",
        "ubicacionDelGrifo": "lavamanos atado culata/esterilizador",
        "estado": null,
        "frecuenciaDeMuestreo": "semestral"
    },
    {
        "sector": "faena",
        "numeroDeGrifo": "167",
        "ubicacionDelGrifo": "lavamanos  lavado de cabezas",
        "estado": null,
        "frecuenciaDeMuestreo": "semestral"
    },
    {
        "sector": "faena",
        "numeroDeGrifo": "168",
        "ubicacionDelGrifo": "pico lavado de bandejas",
        "estado": null,
        "frecuenciaDeMuestreo": "semestral"
    },
    {
        "sector": "faena",
        "numeroDeGrifo": "169",
        "ubicacionDelGrifo": "lavamanos inspeccion veterinaria/esterilizador",
        "estado": null,
        "frecuenciaDeMuestreo": "semestral"
    },
    {
        "sector": "menudencias rojas",
        "numeroDeGrifo": "170",
        "ubicacionDelGrifo": "lavamanos lado izquierdo de noria /esterilizador",
        "estado": null,
        "frecuenciaDeMuestreo": "semestral"
    },
    {
        "sector": "menudencias rojas",
        "numeroDeGrifo": "171",
        "ubicacionDelGrifo": "lavamanos riñón",
        "estado": "22/3/2024 jabonera rota 18/4/2024",
        "frecuenciaDeMuestreo": "semestral"
    },
    {
        "sector": "menudencias rojas",
        "numeroDeGrifo": "172",
        "ubicacionDelGrifo": "lavamanos lado derecho noria /esterilizador",
        "estado": "18/4/2024",
        "frecuenciaDeMuestreo": "semestral"
    },
    {
        "sector": "menudencias rojas",
        "numeroDeGrifo": "173",
        "ubicacionDelGrifo": "lavamanos extracción de quijada/esterilizador",
        "estado": "18/4/2024 cambiar cepillo",
        "frecuenciaDeMuestreo": "semestral"
    },
    {
        "sector": "menudencias rojas",
        "numeroDeGrifo": "174",
        "ubicacionDelGrifo": "esterilizador (limpieza)",
        "estado": "18/4/2024 presencia de oxido",
        "frecuenciaDeMuestreo": "semestral"
    },
    {
        "sector": "menudencias rojas",
        "numeroDeGrifo": "175",
        "ubicacionDelGrifo": "esterilizador",
        "estado": "18/4/2024",
        "frecuenciaDeMuestreo": "trimestral"
    },
    {
        "sector": "pasillo",
        "numeroDeGrifo": "176",
        "ubicacionDelGrifo": "pico (limpieza)",
        "estado": "18/4/2024",
        "frecuenciaDeMuestreo": "anual"
    },
    {
        "sector": "afiladero faena",
        "numeroDeGrifo": "177",
        "ubicacionDelGrifo": "lavamanos afilareo",
        "estado": "18/4/2024",
        "frecuenciaDeMuestreo": "anual"
    },
    {
        "sector": "pasillo",
        "numeroDeGrifo": "178",
        "ubicacionDelGrifo": "registro\npico (limpieza)",
        "estado": "18/4/2024",
        "frecuenciaDeMuestreo": "anual"
    },
    {
        "sector": "filtro faena zona interm.",
        "numeroDeGrifo": "179",
        "ubicacionDelGrifo": "lavamanos ingreso a faena",
        "estado": "18/4/2024",
        "frecuenciaDeMuestreo": "anual                   3"
    },
    {
        "sector": "filtro principal",
        "numeroDeGrifo": "180",
        "ubicacionDelGrifo": "lavamanos",
        "estado": "18/4/2024",
        "frecuenciaDeMuestreo": "anual"
    },
    {
        "sector": "vestuario despostada caballeros",
        "numeroDeGrifo": "181",
        "ubicacionDelGrifo": "lavamanos",
        "estado": "18/4/2024",
        "frecuenciaDeMuestreo": "anual"
    },
    {
        "sector": "vestuario despostada",
        "numeroDeGrifo": "182",
        "ubicacionDelGrifo": "lavamanos",
        "estado": "18/4/2024",
        "frecuenciaDeMuestreo": "anual"
    },
    {
        "sector": "vestuario despostada",
        "numeroDeGrifo": "183",
        "ubicacionDelGrifo": "lavamanos",
        "estado": "18/4/2024",
        "frecuenciaDeMuestreo": "anual"
    },
    {
        "sector": "enfermeria",
        "numeroDeGrifo": "184",
        "ubicacionDelGrifo": "lavamanos entrada",
        "estado": "18/4/2024",
        "frecuenciaDeMuestreo": "anual"
    },
    {
        "sector": "enfermeria",
        "numeroDeGrifo": "185",
        "ubicacionDelGrifo": "lavamanos consultorio",
        "estado": "18/4/2024",
        "frecuenciaDeMuestreo": "anual"
    },
    {
        "sector": "enfermeria",
        "numeroDeGrifo": "186",
        "ubicacionDelGrifo": "lavamanos baño",
        "estado": "18/4/2024",
        "frecuenciaDeMuestreo": "anual"
    },
    {
        "sector": "sistemas baño",
        "numeroDeGrifo": "187",
        "ubicacionDelGrifo": "lavamanos baño",
        "estado": "18/4/2024",
        "frecuenciaDeMuestreo": "anual"
    },
    {
        "sector": "faena",
        "numeroDeGrifo": "188",
        "ubicacionDelGrifo": "pico cabina lavado de cabezas y lengua",
        "estado": "18/4/2024",
        "frecuenciaDeMuestreo": "trimestral"
    },
    {
        "sector": "faena",
        "numeroDeGrifo": "189",
        "ubicacionDelGrifo": "pico lavamanos puesto de caravanas",
        "estado": "18/4/2024",
        "frecuenciaDeMuestreo": "anual"
    },
    {
        "sector": "faena",
        "numeroDeGrifo": "190",
        "ubicacionDelGrifo": "lavamanos rajada de pecho/esterilizador",
        "estado": "18/4/2024",
        "frecuenciaDeMuestreo": "anual"
    },
    {
        "sector": "faena",
        "numeroDeGrifo": "191",
        "ubicacionDelGrifo": "lavamanos desollador/esterilizador",
        "estado": "18/4/2024",
        "frecuenciaDeMuestreo": "trimestral"
    },
    {
        "sector": "faena",
        "numeroDeGrifo": "192",
        "ubicacionDelGrifo": "lavamanos empaque primario menudencias",
        "estado": "18/4/2024",
        "frecuenciaDeMuestreo": "anual"
    },
    {
        "sector": "faena",
        "numeroDeGrifo": "193",
        "ubicacionDelGrifo": "lavamanos empaque secundrio menudencias/esterilizador",
        "estado": "18/4/2024",
        "frecuenciaDeMuestreo": "anual"
    },
    {
        "sector": "faena",
        "numeroDeGrifo": "194",
        "ubicacionDelGrifo": "lavamanos cuereado de cabeza/esterilizador",
        "estado": "18/4/2024",
        "frecuenciaDeMuestreo": "semestral"
    },
    {
        "sector": "faena",
        "numeroDeGrifo": "195",
        "ubicacionDelGrifo": "lavamanos vacuna y ganglios/esterilizador",
        "estado": "18/4/2024",
        "frecuenciaDeMuestreo": "semestral"
    },
    {
        "sector": "vestuario despostada\ndamas",
        "numeroDeGrifo": "196",
        "ubicacionDelGrifo": "lavamanos de ingreso a vestuario",
        "estado": "18/4/2024",
        "frecuenciaDeMuestreo": "semestral"
    },
    {
        "sector": "saladero de menudencias",
        "numeroDeGrifo": "197",
        "ubicacionDelGrifo": "lavamanos de menudencias rojas",
        "estado": "18/4/2024",
        "frecuenciaDeMuestreo": "semestral"
    },
    {
        "sector": "menudencias rojas",
        "numeroDeGrifo": "198",
        "ubicacionDelGrifo": "pico lavadero de canastos",
        "estado": null,
        "frecuenciaDeMuestreo": null
    },
    {
        "sector": "cuarteo",
        "numeroDeGrifo": "200",
        "ubicacionDelGrifo": "lavamanos filtro sanitario",
        "estado": "18/4/2024",
        "frecuenciaDeMuestreo": "anual"
    },
    {
        "sector": "cuarteo",
        "numeroDeGrifo": "201",
        "ubicacionDelGrifo": "lavamanos palco  /esterilizador",
        "estado": "18/4/2024",
        "frecuenciaDeMuestreo": "semestral"
    },
    {
        "sector": "cuarteo",
        "numeroDeGrifo": "202",
        "ubicacionDelGrifo": "lavamanos principal",
        "estado": "|",
        "frecuenciaDeMuestreo": "anual"
    },
    {
        "sector": "pasillo de cuarteo",
        "numeroDeGrifo": "203",
        "ubicacionDelGrifo": "pico cámaras",
        "estado": "18/4/2024",
        "frecuenciaDeMuestreo": "semestral"
    },
    {
        "sector": "depósito de insumos",
        "numeroDeGrifo": "204",
        "ubicacionDelGrifo": "lavamanos filtro sanitario",
        "estado": "18/4/2024",
        "frecuenciaDeMuestreo": "anual"
    },
    {
        "sector": "cuarteo",
        "numeroDeGrifo": "205",
        "ubicacionDelGrifo": "esterilizador",
        "estado": null,
        "frecuenciaDeMuestreo": null
    },
    {
        "sector": "depósito de insumos",
        "numeroDeGrifo": "206",
        "ubicacionDelGrifo": "pico alimentacion para limpieza",
        "estado": null,
        "frecuenciaDeMuestreo": null
    },
    {
        "sector": "despostada",
        "numeroDeGrifo": "300",
        "ubicacionDelGrifo": "lavamanos filtro sanitario",
        "estado": "26/4/2024",
        "frecuenciaDeMuestreo": "anual"
    },
    {
        "sector": "despostada",
        "numeroDeGrifo": "301",
        "ubicacionDelGrifo": "lavamanos  pared charqueo asado/esterilizador",
        "estado": "26/4/2024",
        "frecuenciaDeMuestreo": "semestral"
    },
    {
        "sector": "despostada",
        "numeroDeGrifo": "302",
        "ubicacionDelGrifo": "lavamanos  pared charqueo asado/esterilizador",
        "estado": "26/4/2024",
        "frecuenciaDeMuestreo": "semestral"
    },
    {
        "sector": "despostada",
        "numeroDeGrifo": "303",
        "ubicacionDelGrifo": "lavamanos  pared charqueo calado asado/esterilizador",
        "estado": "26/4/2024",
        "frecuenciaDeMuestreo": "semestral"
    },
    {
        "sector": "despostada",
        "numeroDeGrifo": "304",
        "ubicacionDelGrifo": "lavamanos palco desposte /esterilizador",
        "estado": "26/4/2024",
        "frecuenciaDeMuestreo": "semestral"
    },
    {
        "sector": "despostada",
        "numeroDeGrifo": "305",
        "ubicacionDelGrifo": "lavamanos palco desposte /esterilizador",
        "estado": "26/4/2024",
        "frecuenciaDeMuestreo": "semestral"
    },
    {
        "sector": "despostada",
        "numeroDeGrifo": "306",
        "ubicacionDelGrifo": "lavamanos palco desposte/esterilizador",
        "estado": "26/4/2024",
        "frecuenciaDeMuestreo": "semestral"
    },
    {
        "sector": "despostada",
        "numeroDeGrifo": "307",
        "ubicacionDelGrifo": "lavamanos palco desposte/esterilizador",
        "estado": "26/4/2024",
        "frecuenciaDeMuestreo": "semestral"
    },
    {
        "sector": "despostada",
        "numeroDeGrifo": "308",
        "ubicacionDelGrifo": "lavamanos palco desposte/esterilizador",
        "estado": "26/4/2024",
        "frecuenciaDeMuestreo": "semestral"
    },
    {
        "sector": "despostada",
        "numeroDeGrifo": "309",
        "ubicacionDelGrifo": "lavamanos palco desposte/esterilizador",
        "estado": "26/4/2024",
        "frecuenciaDeMuestreo": "semestral"
    },
    {
        "sector": "despostada",
        "numeroDeGrifo": "310",
        "ubicacionDelGrifo": "lavamanos sala de afilado/esterilizador",
        "estado": "26/4/2024",
        "frecuenciaDeMuestreo": "anual"
    },
    {
        "sector": "despostada",
        "numeroDeGrifo": "311",
        "ubicacionDelGrifo": "lavamanos palco dressing/esterilizador",
        "estado": "26/4/2024",
        "frecuenciaDeMuestreo": "semestral"
    },
    {
        "sector": "despostada",
        "numeroDeGrifo": "312",
        "ubicacionDelGrifo": "lavamanos palco desposte/esterilizador",
        "estado": "26/4/2024",
        "frecuenciaDeMuestreo": "semestral"
    },
    {
        "sector": "despostada",
        "numeroDeGrifo": "313",
        "ubicacionDelGrifo": "lavamanos pared charqueo/esterilizador",
        "estado": "26/4/2024",
        "frecuenciaDeMuestreo": "semestral"
    },
    {
        "sector": "despostada",
        "numeroDeGrifo": "314",
        "ubicacionDelGrifo": "lavamanos pared charqueo/esterilizador",
        "estado": "26/4/2024",
        "frecuenciaDeMuestreo": "semestral"
    },
    {
        "sector": "despostada",
        "numeroDeGrifo": "315",
        "ubicacionDelGrifo": "lavamanos pared charqueo/esterilizador",
        "estado": "26/4/2024",
        "frecuenciaDeMuestreo": "semestral"
    },
    {
        "sector": "despostada",
        "numeroDeGrifo": "316",
        "ubicacionDelGrifo": "lavamanos pared charqueo/esterilizador",
        "estado": "26/4/2024",
        "frecuenciaDeMuestreo": "semestral"
    },
    {
        "sector": "despostada",
        "numeroDeGrifo": "317",
        "ubicacionDelGrifo": "lavamanos pared charqueo/esterilizador",
        "estado": "26/4/2024",
        "frecuenciaDeMuestreo": "semestral"
    },
    {
        "sector": "despostada",
        "numeroDeGrifo": "318",
        "ubicacionDelGrifo": "lavamanos central charqueo /esterilizador",
        "estado": "26/4/2024",
        "frecuenciaDeMuestreo": "semestral"
    },
    {
        "sector": "despostada",
        "numeroDeGrifo": "319",
        "ubicacionDelGrifo": "lavamanos central charqueo /esterilizador",
        "estado": "26/4/2024",
        "frecuenciaDeMuestreo": "semestral"
    },
    {
        "sector": "despostada",
        "numeroDeGrifo": "320",
        "ubicacionDelGrifo": "lavamanos central charqueo /esterilizador",
        "estado": "26/4/2024",
        "frecuenciaDeMuestreo": "semestral"
    },
    {
        "sector": "despostada",
        "numeroDeGrifo": "321",
        "ubicacionDelGrifo": "lavamanos central charqueo /esterilizador",
        "estado": "26/4/2024",
        "frecuenciaDeMuestreo": "semestral"
    },
    {
        "sector": "despostada",
        "numeroDeGrifo": "322",
        "ubicacionDelGrifo": "lavamanos reinspección veterinaria/esterilizador",
        "estado": "26/4/2024 no funciona es urgente",
        "frecuenciaDeMuestreo": "semestral"
    },
    {
        "sector": "despostada",
        "numeroDeGrifo": "323",
        "ubicacionDelGrifo": "pico bajada agua sala de afilado",
        "estado": "26/4/2024",
        "frecuenciaDeMuestreo": "anual"
    },
    {
        "sector": "despostada",
        "numeroDeGrifo": "324",
        "ubicacionDelGrifo": "pico agua reinspección veterinaria",
        "estado": "26/4/2024",
        "frecuenciaDeMuestreo": "anual"
    },
    {
        "sector": "despostada",
        "numeroDeGrifo": "325",
        "ubicacionDelGrifo": "pico bajada agua escalera",
        "estado": "26/4/2024",
        "frecuenciaDeMuestreo": "anual"
    },
    {
        "sector": "despostada",
        "numeroDeGrifo": "326",
        "ubicacionDelGrifo": "pico bajada agua saladero",
        "estado": "26/4/2024",
        "frecuenciaDeMuestreo": "anual"
    },
    {
        "sector": "saladero",
        "numeroDeGrifo": "327",
        "ubicacionDelGrifo": "lavamanos ingreso",
        "estado": "26/4/2024",
        "frecuenciaDeMuestreo": "anual"
    },
    {
        "sector": "saladero",
        "numeroDeGrifo": "328",
        "ubicacionDelGrifo": "lavamanos palco/esterilizador",
        "estado": "26/4/2024",
        "frecuenciaDeMuestreo": "semestral"
    },
    {
        "sector": "saladero",
        "numeroDeGrifo": "329",
        "ubicacionDelGrifo": "registro\npico alimentación piletas de lavado y duchas",
        "estado": "26/4/2024",
        "frecuenciaDeMuestreo": "trimestral"
    },
    {
        "sector": "saladero",
        "numeroDeGrifo": "330",
        "ubicacionDelGrifo": "pico alimentación piletas de remojo",
        "estado": "26/4/2024",
        "frecuenciaDeMuestreo": "trimestral               4"
    },
    {
        "sector": "saladero",
        "numeroDeGrifo": "331",
        "ubicacionDelGrifo": "pico alimentacion para limpieza",
        "estado": "26/4/2024",
        "frecuenciaDeMuestreo": "trimestral"
    },
    {
        "sector": "depósito de insumos",
        "numeroDeGrifo": "332",
        "ubicacionDelGrifo": "libre",
        "estado": "26/4/2024",
        "frecuenciaDeMuestreo": "trimestral"
    },
    {
        "sector": "despostada",
        "numeroDeGrifo": "333",
        "ubicacionDelGrifo": "lavamanos frente a puesto de pesaje /esterilizador",
        "estado": "26/4/2024",
        "frecuenciaDeMuestreo": "trimestral"
    },
    {
        "sector": "empaque secundario",
        "numeroDeGrifo": "334",
        "ubicacionDelGrifo": "pico limpieza empaque secundario",
        "estado": null,
        "frecuenciaDeMuestreo": null
    },
    {
        "sector": "empaque secundario",
        "numeroDeGrifo": "335",
        "ubicacionDelGrifo": "pico limpieza empaque secundario",
        "estado": null,
        "frecuenciaDeMuestreo": null
    },
    {
        "sector": "saladero",
        "numeroDeGrifo": "336",
        "ubicacionDelGrifo": "pico pileta remojo",
        "estado": null,
        "frecuenciaDeMuestreo": null
    },
    {
        "sector": "saladero",
        "numeroDeGrifo": "337",
        "ubicacionDelGrifo": "pico limpieza",
        "estado": null,
        "frecuenciaDeMuestreo": null
    }
]